indep_free/cli.py
indep_free/downloader.py
indep_free/mailer.py
indep_free/manager.py
indep_free/utils.py
indep_free-0.3.2.dist-info/entry_points.txt
indep_free-0.3.2.dist-info/LICENSE
indep_free-0.3.2.dist-info/WHEEL
indep_free-0.3.2.dist-info/METADATA
indep_free-0.3.2.dist-info/RECORD
