Metadata-Version: 2.1
Name: indep-free
Version: 0.3.2
Summary: Send newspaper "El Independiente" to mail. While we can download the newspaper and sed via email.
License: GPL-3+
Author: Emmanuel Arias
Author-email: eamanu@yaerobi.com
Requires-Python: >=3.6,<4.0
Classifier: License :: Other/Proprietary License
Classifier: Programming Language :: Python :: 3
Classifier: Programming Language :: Python :: 3.6
Classifier: Programming Language :: Python :: 3.7
Classifier: Programming Language :: Python :: 3.8
Classifier: Programming Language :: Python :: 3.9
Requires-Dist: PyDrive (>=1.3.1,<2.0.0)
Requires-Dist: requests (>=2.25.1,<3.0.0)
